ethereum/__init__.py
ethereum/abi.py
ethereum/block.py
ethereum/bloom.py
ethereum/child_dao_list.py
ethereum/common.py
ethereum/compress.py
ethereum/config.py
ethereum/consensus_strategy.py
ethereum/db.py
ethereum/exceptions.py
ethereum/fast_rlp.py
ethereum/fastvm.py
ethereum/genesis_helpers.py
ethereum/messages.py
ethereum/meta.py
ethereum/new_state.py
ethereum/opcodes.py
ethereum/securetrie.py
ethereum/slogging.py
ethereum/snapshot.py
ethereum/specials.py
ethereum/state.py
ethereum/transaction_queue.py
ethereum/transactions.py
ethereum/trie.py
ethereum/utils.py
ethereum/vm.py
ethereum/experimental/__init__.py
ethereum/experimental/fastvm.py
ethereum/experimental/pruning_trie.py
ethereum/experimental/refcount_db.py
ethereum/experimental/spv.py
ethereum/hybrid_casper/__init__.py
ethereum/hybrid_casper/casper_initiating_transactions.py
ethereum/hybrid_casper/casper_utils.py
ethereum/hybrid_casper/chain.py
ethereum/hybrid_casper/consensus.py
ethereum/hybrid_casper/validator.py
ethereum/pow/__init__.py
ethereum/pow/chain.py
ethereum/pow/consensus.py
ethereum/pow/ethash.py
ethereum/pow/ethash_utils.py
ethereum/pow/ethpow.py
ethereum/tests/__init__.py
ethereum/tests/test_abi.py
ethereum/tests/test_blocks.py
ethereum/tests/test_bloom.py
ethereum/tests/test_chain.py
ethereum/tests/test_compress.py
ethereum/tests/test_contracts.py
ethereum/tests/test_db.py
ethereum/tests/test_difficulty.py
ethereum/tests/test_genesis.py
ethereum/tests/test_keys.py
ethereum/tests/test_opcodes.py
ethereum/tests/test_serialization.py
ethereum/tests/test_state.py
ethereum/tests/test_tester.py
ethereum/tests/test_transactions.py
ethereum/tests/test_trie.py
ethereum/tests/test_trie_next_prev.py
ethereum/tests/utils.py
ethereum/tools/__init__.py
ethereum/tools/_solidity.py
ethereum/tools/keys.py
ethereum/tools/new_statetest_utils.py
ethereum/tools/tester.py
ethereum/tools/testing_lang.py
ethereum/tools/testutils.py
ethereum_augur_temp-2.1.10.dist-info/DESCRIPTION.rst
ethereum_augur_temp-2.1.10.dist-info/METADATA
ethereum_augur_temp-2.1.10.dist-info/RECORD
ethereum_augur_temp-2.1.10.dist-info/WHEEL
ethereum_augur_temp-2.1.10.dist-info/metadata.json
ethereum_augur_temp-2.1.10.dist-info/top_level.txt
