Metadata-Version: 2.0
Name: ethereum-augur-temp
Version: 2.1.10
Summary: Next generation cryptocurrency network
Home-page: https://github.com/ethereum/pyethereum/
Author: UNKNOWN
Author-email: UNKNOWN
License: UNKNOWN
Platform: UNKNOWN
Classifier: Intended Audience :: Developers
Classifier: Natural Language :: English
Classifier: Programming Language :: Python :: 2
Classifier: Programming Language :: Python :: 2.7
Classifier: Programming Language :: Python :: 3
Classifier: Programming Language :: Python :: 3.5
Classifier: Programming Language :: Python :: 3.6
Requires-Dist: PyYAML
Requires-Dist: coincurve (>=5.0.1)
Requires-Dist: pbkdf2
Requires-Dist: py-ecc
Requires-Dist: pycryptodome (==3.4.6)
Requires-Dist: pyethash
Requires-Dist: pysha3 (>=1.0.1)
Requires-Dist: repoze.lru
Requires-Dist: rlp (>=0.4.7)
Requires-Dist: scrypt
